astvalidate/__init__.py
astvalidate/__main__.py
astvalidate/compatibility.py
astvalidate/context.py
astvalidate/validators/__init__.py
astvalidate/validators/base.py
astvalidate/validators/contextual.py
astvalidate/validators/simple.py
astvalidate/validators/symbolic.py
astvalidate/validators/syntatical.py
astvalidate-2021.12.31.dist-info/LICENSE.txt
astvalidate-2021.12.31.dist-info/METADATA
astvalidate-2021.12.31.dist-info/WHEEL
astvalidate-2021.12.31.dist-info/top_level.txt
astvalidate-2021.12.31.dist-info/RECORD
