Metadata-Version: 2.1
Name: astvalidate
Version: 2021.12.31
Summary: Advanced AST validation
Home-page: https://github.com/isidentical/astvalidate
Author: isidentical
Author-email: isidentical@gmail.com
License: UNKNOWN
Platform: UNKNOWN
Requires-Python: >=3.8
License-File: LICENSE.txt
